{"cameraMode":{"drawMode":0,"name":"Shaded","section":"Shading Mode"},"sceneLighting":false,"audioPlay":false,"sceneViewState":{"m_AlwaysRefresh":false,"showFog":true,"showSkybox":false,"showFlares":true,"showImageEffects":true,"showParticleSystems":true,"showVisualEffectGraphs":true,"m_FxEnabled":true},"in2DMode":false,"pivot":{"x":0.0,"y":5.960464477539063e-8,"z":-1.1920928955078126e-7},"rotation":{"x":-0.013583844527602196,"y":-0.9791059494018555,"z":0.1906471848487854,"w":-0.06971342116594315},"size":8.223023414611817,"orthographic":false}